{
    "0.12942906996740644-3-22": {
        "average clique similarity": 0.12942906996740644,
        "clique": [
            "1-Nathan Deal  R  sign",
            "3-   David Mack  Hurri",
            "0-But hurricanes often"
        ],
        "median tf-idf score": 0.7417807263521772,
        "publications": [
            "Washington Post",
            "New York Times",
            "Buzzfeed News"
        ],
        "sentences": [
            "Nathan Deal (R) signed an executive order declaring an emergency for a week in 1    Caption   The Category 3 hurricane slammed the eastern tip of Cuba and ravaged Haiti on its way to the East Coast and the Bahamas.",
            "\u2014  David Mack, Hurricane Matthew has already caused the death of a fisherman in Haiti as its outer bands brought high winds and rains to the waters around the island, the Associated Press reported.",
            "But hurricanes often spread well beyond the edges of the cone, and so your mother could expect high winds, a ton of rain to deal with, and the usual run on supplies."
        ],
        "tf-idf score": [
            0.7417807263521772,
            0.7934746389901993,
            0.42981688550162284
        ]
    },
    "0.13497822363004894-3-343": {
        "average clique similarity": 0.13497822363004894,
        "clique": [
            "3- We are closely moni",
            "4-You need to leave   ",
            "1-He said that his fam"
        ],
        "median tf-idf score": 0.4390307069566248,
        "publications": [
            "Washington Post",
            "NPR",
            "Buzzfeed News"
        ],
        "sentences": [
            "\u201cWe are closely monitoring the storm\u2019s progress,\u201d he said.",
            "You need to leave,\u201d he said on Thursday morning.",
            "He said that his family lived inland during Hurricane Wilma, which he called \u201cdevastating."
        ],
        "tf-idf score": [
            0.4390307069566248,
            0.3574031556751589,
            0.5591989913395208
        ]
    },
    "0.15233246072337914-3-9": {
        "average clique similarity": 0.15233246072337914,
        "clique": [
            "0-I live in Jacksonvil",
            "2-I live in a solid co",
            "3- As the Red Cross ge"
        ],
        "median tf-idf score": 0.09010258949441814,
        "publications": [
            "New York Times",
            "Buzzfeed News",
            "CNN"
        ],
        "sentences": [
            "I live in Jacksonville, N C Should we be looking to evacuate anytime soon?",
            "I live in a solid concrete condo.",
            "\u201cAs the Red Cross gets ready, we urge people who may live in the path of this storm to make their own preparations now."
        ],
        "tf-idf score": [
            0.09010258949441814,
            0.03329779132378773,
            0.44137756857343763
        ]
    },
    "0.15303687772997435-3-782": {
        "average clique similarity": 0.15303687772997435,
        "clique": [
            "0-John rode out his fi",
            "1-Oct  5  2016 A man t",
            "2-In fact  a sign outs"
        ],
        "median tf-idf score": 0.32969596350991537,
        "publications": [
            "CNN",
            "New York Times",
            "Washington Post"
        ],
        "sentences": [
            "John rode out his first hurricane, Carla, in his hometown, Galveston, Tex.",
            "Oct. 5, 2016 A man talks on his cellphone while searching for belongings amid the rubble of his home destroyed by Hurricane Matthew in Baracoa, Cuba.",
            "In fact, a sign outside declares his bar open: \u201dHonk for hurricane party inside\u201d."
        ],
        "tf-idf score": [
            0.28631942596354004,
            0.5145585534122663,
            0.32969596350991537
        ]
    },
    "0.1542989409417004-3-707": {
        "average clique similarity": 0.1542989409417004,
        "clique": [
            "1-After Hurricane Matt",
            "4-Haley told residents",
            "2-  Based on the lates"
        ],
        "median tf-idf score": 0.7864895843346655,
        "publications": [
            "CNN",
            "Washington Post",
            "NPR"
        ],
        "sentences": [
            "After Hurricane Matthew pummeled Haiti on Tuesday  \u2014   causing at least 11 deaths there and in the Dominican Republic, officials said, with the full toll still unknown  \u2014   it weakened slightly before continuing on to the Bahamas and barreling onward to Florida, where forecasters warn it could lead to \u201c \u201d along the state\u2019s eastern coast.",
            "Haley told residents that it was still possible that Matthew, too, would shift away, but based on current forecasts, residents should travel at least 100 miles from the coast.",
            "\u2022 Based on the latest projections, Matthew could make landfall in Florida as a Category 4 storm, or it could skirt the coast and head north before possibly heading back toward land."
        ],
        "tf-idf score": [
            1.2589399775496668,
            0.5636686293191338,
            0.7864895843346655
        ]
    },
    "0.15973771225163755-3-124": {
        "average clique similarity": 0.15973771225163755,
        "clique": [
            "0-I m sure these const",
            "2-Are we prepared for ",
            "3- We ve been through "
        ],
        "median tf-idf score": 0.2971490311840787,
        "publications": [
            "CNN",
            "Buzzfeed News",
            "New York Times"
        ],
        "sentences": [
            "I\u2019m sure these construction firms have storm protocol, but it\u2019s been a while since we had a major storm.",
            "Are we prepared for a major hurricane?",
            "\u201cWe\u2019ve been through winter storms, We\u2019ve been through a   flood,\u201d she said."
        ],
        "tf-idf score": [
            0.2560850212366077,
            0.2971490311840787,
            0.440716706114944
        ]
    },
    "0.16087409673413297-3-36": {
        "average clique similarity": 0.16087409673413297,
        "clique": [
            "0-Will we have a probl",
            "3-    Tasneem Nashrull",
            "2- We re just going to"
        ],
        "median tf-idf score": 0.35028885848707025,
        "publications": [
            "Buzzfeed News",
            "CNN",
            "New York Times"
        ],
        "sentences": [
            "Will we have a problem finding gasoline?",
            "\u2014   Tasneem Nashrulla, #Matthew will not have a lot of land to interact with before it gets to FL Floridians have to prepare for a major hurricane.",
            "\u201dWe\u2019re just going to have to play it by ear and have our resources ready,\u201d the governor has said."
        ],
        "tf-idf score": [
            0.015120886874670909,
            0.48136462919162426,
            0.35028885848707025
        ]
    },
    "0.1617714792539069-3-501": {
        "average clique similarity": 0.1617714792539069,
        "clique": [
            "4-For Florida resident",
            "1-Even as they prepare",
            "2-In Savannah  Mayor E"
        ],
        "median tf-idf score": 0.5955720095225863,
        "publications": [
            "NPR",
            "Washington Post",
            "CNN"
        ],
        "sentences": [
            "For Florida residents who think they can ride out Hurricane Matthew, Gov.",
            "Even as they prepared, people who have lived through storms before said they were worried about the effect.",
            "In Savannah, Mayor Eddie DeLoach warned those who stay that they\u2019d be on their own."
        ],
        "tf-idf score": [
            0.6820845763104117,
            0.5955720095225863,
            0.10179198995702309
        ]
    },
    "0.16466901239584866-3-295": {
        "average clique similarity": 0.16466901239584866,
        "clique": [
            "3-  By nightfall on Tu",
            "2-  The storm has kill",
            "0-    AZAM AHMED Initi"
        ],
        "median tf-idf score": 0.5747343748309972,
        "publications": [
            "Buzzfeed News",
            "CNN",
            "New York Times"
        ],
        "sentences": [
            "\u201d By nightfall on Tuesday, the Associated Press reported at least five people had died in Haiti, where it was feared the hurricane would leave catastrophic destruction.",
            "\u2022 The storm has killed at least 269 people in three Caribbean countries.",
            "\u2014   AZAM AHMED Initial reports from the government of Haiti said that five people there had been killed, 10 people had been injured and one person was missing."
        ],
        "tf-idf score": [
            0.6783886342259076,
            0.41137624890345603,
            0.5747343748309972
        ]
    },
    "0.17002068775849286-3-496": {
        "average clique similarity": 0.17002068775849286,
        "clique": [
            "3-   flash floods and ",
            "0-  Infrastructure in ",
            "4-Hundreds of people d"
        ],
        "median tf-idf score": 0.48035196312514983,
        "publications": [
            "New York Times",
            "Buzzfeed News",
            "NPR"
        ],
        "sentences": [
            "\u201c  flash floods and mudslides are likely from this rainfall in southern and northwestern Haiti, the southwestern Dominican Republic, and eastern Cuba,\u201d the NHC said.",
            "\u201d Infrastructure in the Bahamas, thanks to the heavy tourism industry, is likely to fare better than that of Haiti and Eastern Cuba, where the storm devastated stretches of the island, leaving massive flooding or piles of rubble in its wake.",
            "Hundreds of people died as the storm tore through Haiti, Cuba and the Bahamas, including at least 283 dead in Haiti alone."
        ],
        "tf-idf score": [
            0.4434993517776123,
            0.5433203964708427,
            0.48035196312514983
        ]
    },
    "0.17017251747867965-3-256": {
        "average clique similarity": 0.17017251747867965,
        "clique": [
            "2-  CNN  The National ",
            "3- Matthew is likely t",
            "0-But it s too early t"
        ],
        "median tf-idf score": 0.6145961030942312,
        "publications": [
            "CNN",
            "New York Times",
            "Buzzfeed News"
        ],
        "sentences": [
            " (CNN) The National Weather Service is not mincing words about powerful Hurricane Matthew.",
            "\u201cMatthew is likely to produce devastating impacts\u201d in Haiti, the National Hurricane Center said.",
            "But it\u2019s too early to say where this thing is going with any certainty, so keep watching Matthew at the National Hurricane Center, or your favorite source of weather news."
        ],
        "tf-idf score": [
            0.5643731642848793,
            0.826198108459903,
            0.6145961030942312
        ]
    },
    "0.1702202498987373-3-428": {
        "average clique similarity": 0.1702202498987373,
        "clique": [
            "2-Yet despite all the ",
            "1-Some mandatory evacu",
            "4-Many residents are u"
        ],
        "median tf-idf score": 0.5290627954294731,
        "publications": [
            "Washington Post",
            "CNN",
            "NPR"
        ],
        "sentences": [
            "Yet despite all the warnings, West Palm Beach Mayor Jeri Muoio said not everyone is listening, even with mandatory evacuation orders in place.",
            "Some mandatory evacuations were in place Wednesday in Florida, along with voluntary evacuations in the Lucie, Flagler and Duval counties that are home to more than 1.",
            "Many residents are under voluntary evacuation orders, but mandatory evacuation has been ordered east of Interstate 95 in all six coastal counties  \u2014   an area that includes the city of Savannah."
        ],
        "tf-idf score": [
            0.5290627954294731,
            0.4488906952379467,
            0.5657469144291445
        ]
    },
    "0.17063252031644197-3-155": {
        "average clique similarity": 0.17063252031644197,
        "clique": [
            "2-As thousands fled in",
            "0-Flashlights were put",
            "1-  Guadalupe said his"
        ],
        "median tf-idf score": 0.38235652690445276,
        "publications": [
            "CNN",
            "New York Times",
            "Washington Post"
        ],
        "sentences": [
            "As thousands fled inland, some people said they were staying put.",
            "Flashlights were put within easy reach, and windows and glass doors were shielded by dusty hurricane shutters.",
            "\u201d Guadalupe said his family in Lauderdale by the Sea has put up storm shutters and bought sandbags, but they were having trouble finding the supplies needed to ride out the storm."
        ],
        "tf-idf score": [
            0.38235652690445276,
            0.29794184482163527,
            0.6166120747239698
        ]
    },
    "0.17657610987516245-3-58": {
        "average clique similarity": 0.17657610987516245,
        "clique": [
            "1-     Empty gas pumps",
            "4-1 million people hav",
            "3-Haley urged resident"
        ],
        "median tf-idf score": 0.2713253124547262,
        "publications": [
            "Buzzfeed News",
            "Washington Post",
            "NPR"
        ],
        "sentences": [
            "\u201d    Empty gas pumps at a Shell station outside Charleston, S C on Tuesday after people fill up their cars to leave town.",
            "1 million people have been urged to leave their homes, The Post and Courier reports.",
            "Haley urged residents to fill their cars with gas, take their important documents, get in touch with family, and make a plan for where they could be staying through the weekend."
        ],
        "tf-idf score": [
            0.2713253124547262,
            0.2697337847945943,
            0.2762536988011812
        ]
    },
    "0.1772322434724197-3-801": {
        "average clique similarity": 0.1772322434724197,
        "clique": [
            "4-Along the coast in F",
            "1-Officials including ",
            "3-But officials warned"
        ],
        "median tf-idf score": 0.8939326733665819,
        "publications": [
            "Washington Post",
            "NPR",
            "Buzzfeed News"
        ],
        "sentences": [
            "Along the coast in Florida, Georgia and South Carolina, millions of residents have been urged to head inland as the powerful hurricane makes its approach.",
            "Officials including President Obama in Washington and governors in Florida, Georgia and the Carolinas urges residents to take the storm seriously, pleas that came as Matthew was posed to be the most powerful storm to make landfall in the country in more than a decade.",
            "But officials warned the worst was yet to come and urged Haitians living along rivers and in shantytowns to move to shelters."
        ],
        "tf-idf score": [
            0.8939326733665819,
            1.0851114651625668,
            0.2633508588795804
        ]
    },
    "0.17957223777422493-3-233": {
        "average clique similarity": 0.17957223777422493,
        "clique": [
            "3-  The hurricane has ",
            "2-The center of the st",
            "1-The center also said"
        ],
        "median tf-idf score": 0.949552861749192,
        "publications": [
            "Buzzfeed News",
            "CNN",
            "Washington Post"
        ],
        "sentences": [
            "\u201d The hurricane has already hit the Bahamas and is expected to hit the coast of Florida next before moving toward other parts of the US  At 3 p. m. Wednesday, a mandatory evacuation of Brevard County\u2019s barrier island and Merritt island was implemented.",
            "The center of the storm was moving northwest at 13 mph.",
            "The center also said Wednesday that it was extending hurricane warnings along much of Florida\u2019s eastern coast."
        ],
        "tf-idf score": [
            1.029869188303195,
            0.4056682076467796,
            0.949552861749192
        ]
    },
    "0.18490392054698135-3-825": {
        "average clique similarity": 0.18490392054698135,
        "clique": [
            "1-He added   You can a",
            "4- You and your family",
            "0-You can register to "
        ],
        "median tf-idf score": 0.037098174198691616,
        "publications": [
            "Washington Post",
            "NPR",
            "New York Times"
        ],
        "sentences": [
            "He added: \u201cYou can always rebuild, you can always repair property.",
            "\u201dYou and your family can be among these numbers if you don\u2019t take this seriously.",
            "You can register to receive Kent County, Md."
        ],
        "tf-idf score": [
            0.033204132457627294,
            0.037098174198691616,
            0.06998827169059
        ]
    },
    "0.1901653940503841-3-205": {
        "average clique similarity": 0.1901653940503841,
        "clique": [
            "2-Officials are concer",
            "1-More evacuation plan",
            "4-More than 1 "
        ],
        "median tf-idf score": 0.3651721524966673,
        "publications": [
            "Washington Post",
            "CNN",
            "NPR"
        ],
        "sentences": [
            "Officials are concerned eastern North Carolina areas that were recently flooded will see more rain from Matthew.",
            "More evacuation plans were expected, he said.",
            "More than 1."
        ],
        "tf-idf score": [
            0.40667986599511946,
            0.3651721524966673,
            0.0
        ]
    },
    "0.19098344726245317-3-578": {
        "average clique similarity": 0.19098344726245317,
        "clique": [
            "1- This is a serious s",
            "4-President Obama decl",
            "3-It is critical that "
        ],
        "median tf-idf score": 0.9784404881263395,
        "publications": [
            "Washington Post",
            "Buzzfeed News",
            "NPR"
        ],
        "sentences": [
            "\u201cThis is a serious storm,\u201d President Obama said after he was briefed on hurricane preparations at the Federal Emergency Management Agency (FEMA) headquarters in Washington.",
            "President Obama declared states of emergency in Florida and South Carolina on Thursday ahead of Hurricane Matthew reaching land.",
            "It is critical that President Obama quickly approves this request,\u201d Scott said in a statement."
        ],
        "tf-idf score": [
            0.9784404881263395,
            1.0225099546013696,
            0.35449993693660575
        ]
    },
    "0.19174658103638342-3-191": {
        "average clique similarity": 0.19174658103638342,
        "clique": [
            "1-  Obama had been sch",
            "3-He urged residents t",
            "2-He s been working fo"
        ],
        "median tf-idf score": 0.36553984088780545,
        "publications": [
            "Buzzfeed News",
            "Washington Post",
            "CNN"
        ],
        "sentences": [
            "\u201d Obama had been scheduled to visit Florida for two events Wednesday, but he scrapped that trip due to the storm and went to FEMA for the briefing instead, according to the White House.",
            "He urged residents to prepare for the worst and hope for the best.",
            "He\u2019s been working for three days and in that time has seen the price for a sheet of plywood jump from $15 to $40, he said."
        ],
        "tf-idf score": [
            0.5821469192209895,
            0.16390149085137304,
            0.36553984088780545
        ]
    },
    "0.19622402093350866-3-509": {
        "average clique similarity": 0.19622402093350866,
        "clique": [
            "1-Even before mandator",
            "2-Voluntary and mandat",
            "3-He urged resident on"
        ],
        "median tf-idf score": 0.45569767201555633,
        "publications": [
            "CNN",
            "Buzzfeed News",
            "Washington Post"
        ],
        "sentences": [
            "Even before mandatory evacuations went into effect in the state, roads were already jammed as people tried to leave the region.",
            "Voluntary and mandatory evacuations in the state stretch from Miami to the   border.",
            "He urged resident on the state\u2019s east coast  \u2014   where Matthew is headed  \u2014   plan for evacuations and to leave the area early."
        ],
        "tf-idf score": [
            0.45569767201555633,
            0.29264962187372706,
            0.7103589071410611
        ]
    },
    "0.21051764521211716-3-515": {
        "average clique similarity": 0.21051764521211716,
        "clique": [
            "3- It s not going to b",
            "2-When the winds reall",
            "4- That s not enough  "
        ],
        "median tf-idf score": 0.3477596358913099,
        "publications": [
            "NPR",
            "CNN",
            "Buzzfeed News"
        ],
        "sentences": [
            "\u201cIt\u2019s not going to be a fast evacuation, but what we ask is that you be patient and understand that it could take up to several hours,\u201d she said.",
            "When the winds really pick up, we will not be sending (emergency responders) out,\u201d she said.",
            "\u201dThat\u2019s not enough,\u201d she said, according to The State."
        ],
        "tf-idf score": [
            0.3646347676912037,
            0.3477596358913099,
            0.34286289186501656
        ]
    },
    "0.21746685635173577-3-107": {
        "average clique similarity": 0.21746685635173577,
        "clique": [
            "4-As the   reported ye",
            "3-A United Nations off",
            "0-The top United Natio"
        ],
        "median tf-idf score": 0.47004742863669907,
        "publications": [
            "NPR",
            "Buzzfeed News",
            "New York Times"
        ],
        "sentences": [
            "As the   reported yesterday, Matthew had a devastating impact in Haiti, washing out roads and raising concerns that the country\u2019s cholera crisis could grow even worse.",
            "A United Nations official said it was the worst humanitarian crisis in Haiti since the 2010 earthquake brought devastation.",
            "The top United Nations official in Haiti, Mourad Wahba, described the storm as \u201cthe largest humanitarian event\u201d in the country of 11 million since a devastating earthquake six years ago, with thousands scrambling for shelter."
        ],
        "tf-idf score": [
            0.3624190915610013,
            0.47004742863669907,
            0.5401372550540413
        ]
    },
    "0.2208559723288286-3-453": {
        "average clique similarity": 0.2208559723288286,
        "clique": [
            "1-Forecasts have shift",
            "4-Updated 11 00 p  m  ",
            "2-The caution came as "
        ],
        "median tf-idf score": 0.9593742002385168,
        "publications": [
            "NPR",
            "Washington Post",
            "CNN"
        ],
        "sentences": [
            "Forecasts have shifted Matthew\u2019s track closer and closer to Florida\u2019s populous east coast, which could bring tropical storm or hurricane effects there Thursday and into Friday.",
            "Updated 11:00 p. m. ET with hurricane center report, Hurricane Matthew, moving closer to the eastern Florida coast, dumped heavy rain on the region late Thursday.",
            "The caution came as Matthew\u2019s outer bands raked the Florida peninsula and the eye of the storm moved closer to the state\u2019s east coast."
        ],
        "tf-idf score": [
            1.084656396775744,
            0.9593742002385168,
            0.8131662999302546
        ]
    },
    "0.221922870435879-3-347": {
        "average clique similarity": 0.221922870435879,
        "clique": [
            "0-Rick Scott warned Fl",
            "3-Rick Scott said Matt",
            "1-Rick Scott  R  said "
        ],
        "median tf-idf score": 0.6290635550662487,
        "publications": [
            "Buzzfeed News",
            "Washington Post",
            "New York Times"
        ],
        "sentences": [
            "Rick Scott warned Floridians that the storm was expected to skim the state\u2019s Atlantic coastline so closely that a direct hit could not be ruled out.",
            "Rick Scott said Matthew could bring the biggest evacuation in state history.",
            "Rick Scott (R) said during a news conference."
        ],
        "tf-idf score": [
            0.6721686730027728,
            0.6290635550662487,
            0.29591193394067117
        ]
    },
    "0.2298601523451176-3-693": {
        "average clique similarity": 0.2298601523451176,
        "clique": [
            "3-Marie Alta   directo",
            "0-Haiti s civil protec",
            "2-The majority  264 pe"
        ],
        "median tf-idf score": 0.4053735363978839,
        "publications": [
            "Buzzfeed News",
            "New York Times",
            "CNN"
        ],
        "sentences": [
            "Marie Alta   director of Haiti\u2019s Civil Protection Agency, told the AP the extent of the damage is not yet known.",
            "Haiti\u2019s civil protection agency said a bridge collapse had severed the main highway connecting the south with    the capital.",
            "The majority, 264 people, died in Haiti, said Civil Protection Service spokesman Joseph Edgard Celestin."
        ],
        "tf-idf score": [
            0.2030158397414347,
            0.4053735363978839,
            0.4594057957706379
        ]
    },
    "0.23344130801645513-3-425": {
        "average clique similarity": 0.23344130801645513,
        "clique": [
            "0- It s going to be fa",
            "4- The hype is going t",
            "2-He s not going anywh"
        ],
        "median tf-idf score": 0.07719204152681755,
        "publications": [
            "CNN",
            "NPR",
            "New York Times"
        ],
        "sentences": [
            "\u201cIt\u2019s going to be family time.",
            "\u201dThe hype is going to be worse than the actual storm.",
            "He\u2019s not going anywhere."
        ],
        "tf-idf score": [
            0.07719204152681755,
            0.26005970544316903,
            0.021510495129835973
        ]
    },
    "0.23440549440598443-3-525": {
        "average clique similarity": 0.23440549440598443,
        "clique": [
            "4-Haley had already ta",
            "0-She said that the ev",
            "2-The South Carolina D"
        ],
        "median tf-idf score": 0.45009757803375294,
        "publications": [
            "New York Times",
            "NPR",
            "CNN"
        ],
        "sentences": [
            "Haley had already taken the unprecedented step of ordering all lanes of Interstate 26 in South Carolina to travel west out of Charleston.",
            "She said that the evacuation of Charleston and part of its surrounding area would begin at 3 p. m. Wednesday, and that the authorities would reverse eastbound lanes on Interstate 26.",
            "The South Carolina Department of Transportation changed the directions of eastbound traffic lanes to accommodate the exodus of people leaving coastal cities like Charleston."
        ],
        "tf-idf score": [
            0.30151975207343434,
            0.5424179846985372,
            0.45009757803375294
        ]
    },
    "0.24785622143875652-3-596": {
        "average clique similarity": 0.24785622143875652,
        "clique": [
            "2-  Roughly 26 million",
            "4-5 million people in ",
            "1-2 million people "
        ],
        "median tf-idf score": 0.44352826643328397,
        "publications": [
            "Washington Post",
            "NPR",
            "CNN"
        ],
        "sentences": [
            "\u2022 Roughly 26 million people live in areas that are under a hurricane or tropical storm warning  or watch, and the hurricane will likely cause billions of dollars in damage, CNN Weather\u2019s Dave Hennen said.",
            "5 million people in the state have been \u201durged or ordered to leave the coast,\u201d the wire service wrote.",
            "2 million people."
        ],
        "tf-idf score": [
            1.0888276088792614,
            0.44352826643328397,
            0.11413616324465556
        ]
    },
    "0.2497482949440295-3-634": {
        "average clique similarity": 0.2497482949440295,
        "clique": [
            "0-Nikki R Haley urged ",
            "1-Nikki Haley  R  acti",
            "4-Nikki Haley extended"
        ],
        "median tf-idf score": 0.7166212711168415,
        "publications": [
            "Washington Post",
            "New York Times",
            "NPR"
        ],
        "sentences": [
            "Nikki R Haley urged people to evacuate Charleston, the state\u2019s   city, as the hurricane threatened millions of people along the East Coast.",
            "Nikki Haley (R) activated the South Carolina National Guard and said the state would evacuate coastal communities and close all coastal schools.",
            "Nikki Haley extended the state\u2019s mandatory evacuation to Jasper and Colleton counties."
        ],
        "tf-idf score": [
            0.7641017804599345,
            0.7166212711168415,
            0.344651488894238
        ]
    },
    "0.25188286012784766-3-716": {
        "average clique similarity": 0.25188286012784766,
        "clique": [
            "2-There s no reason to",
            "4- No one should take ",
            "0-Soon there would be "
        ],
        "median tf-idf score": 0.22448014468490166,
        "publications": [
            "CNN",
            "NPR",
            "New York Times"
        ],
        "sentences": [
            "There\u2019s no reason to take a chance,\u201d he said.",
            "\u201dNo one should take any chances,\u201d he said.",
            "Soon there would be no distraction but the storm."
        ],
        "tf-idf score": [
            0.22448014468490166,
            0.21886980762262337,
            0.23371274137053255
        ]
    },
    "0.2534764127889932-3-240": {
        "average clique similarity": 0.2534764127889932,
        "clique": [
            "0- It was the most ter",
            "3-But forecasters expe",
            "4-The storm is strengt"
        ],
        "median tf-idf score": 0.4686474534768414,
        "publications": [
            "New York Times",
            "NPR",
            "Buzzfeed News"
        ],
        "sentences": [
            "\u201cIt was the most terriblest thing I ever saw,\u201d Ms Holmes said, as she walked along the asphalt toward a staging area in front of the convention center.",
            "But forecasters expect it to regain strength as it moves toward the Bahamas.",
            "The storm is strengthening as it batters the Bahamas and moves toward Florida, the National Hurricane Center says."
        ],
        "tf-idf score": [
            0.4686474534768414,
            0.07223777065543772,
            0.7965832656658567
        ]
    },
    "0.261272747086339-3-605": {
        "average clique similarity": 0.261272747086339,
        "clique": [
            "3-Scott activated 1  0",
            "0-  The governors of F",
            "1-     Thrown for a lo"
        ],
        "median tf-idf score": 0.5990290641988651,
        "publications": [
            "Buzzfeed News",
            "Washington Post",
            "New York Times"
        ],
        "sentences": [
            "Scott activated 1, 000 National Guard Members in addition to the 1, 500 members already positioned between North, Central and South Florida.",
            "\u2022 The governors of Florida, Georgia, South Carolina and North Carolina declared emergencies, and more than 7, 800 National Guard soldiers were activated or placed on alert.",
            "\u201d   [Thrown for a loop: Matthew\u2019s forecast track could rank among \u2018weirdos\u2019 in hurricane history]   Scott closed state offices in more than two dozen Florida counties and said he activated 500 members of the Florida National Guard with another 6, 000 ready to be deployed as needed."
        ],
        "tf-idf score": [
            0.4551503239953456,
            0.5990290641988651,
            1.228478926212948
        ]
    },
    "0.2630320978497713-3-200": {
        "average clique similarity": 0.2630320978497713,
        "clique": [
            "3-The hurricane was fo",
            "2-Forecasters predict ",
            "0-  But Florida  espec"
        ],
        "median tf-idf score": 0.5667924557660905,
        "publications": [
            "Buzzfeed News",
            "CNN",
            "New York Times"
        ],
        "sentences": [
            "The hurricane was forecast to dump   inches of rain on eastern Cuba with isolated areas seeing as much as 20 inches.",
            "Forecasters predict storm surge is some areas could be as high as 11 feet and as many as 15 inches of rain could fall.",
            "\u201d But Florida, especially, has been warned to batten down, and much of the East Coast is preparing for powerful winds and storm surge as well as torrential rain."
        ],
        "tf-idf score": [
            0.5667924557660905,
            0.41325757343970265,
            0.7195349426758691
        ]
    },
    "0.2645808098098339-3-154": {
        "average clique similarity": 0.2645808098098339,
        "clique": [
            "3- What We Know So Far",
            "1- Hurricane Matthew t",
            "0-As the National Hurr"
        ],
        "median tf-idf score": 1.7535874571672498,
        "publications": [
            "Washington Post",
            "Buzzfeed News",
            "New York Times"
        ],
        "sentences": [
            "\u2019What We Know So Far\u2019 \u2019Forecast Track Map\u2019 \u2019Florida governor asks Obama to declare state of emergency ahead of Hurricane Matthew\u2019 \u2019Southeast prepares as Hurricane Matthew takes aim at US\u2019 \u2019Florida and South Carolina residents begin evacuating to higher ground\u2019 \u2019Hurricane warnings remain in place for Florida\u2019s south coast.\u2019 \u2019At least 11 dead as Hurricane Matthew continues\u2019 \u2019Florida beaches now facing hurricane warning\u2019 \u2019Hurricane Matthew makes landfall in Eastern Cuba\u2019 \u2019South Carolina governor calls for 1 million residents to evacuate\u2019 \u2019The US has provided $400, 000 in initial relief assistance to Haiti and Jamaica\u2019 \u2019Florida Gov.",
            "[Hurricane Matthew turns to Florida and it could make landfall as a Category 4]   Matthew was expected to approach the east coast of Florida on Thursday evening, hours after tropical storm conditions could begin in the state, and it could remain at a Category 3 or become even stronger by that point, the National Hurricane Center said.",
            "As the National Hurricane Center put it Thursday evening, \u201cWhen a hurricane is forecast to take a track roughly parallel to a coastline, as Matthew is forecast to do from Florida through South Carolina, it becomes very difficult to estimate impacts this far in advance."
        ],
        "tf-idf score": [
            1.787489363997391,
            1.7535874571672498,
            0.9816119767718852
        ]
    },
    "0.26493746174149974-3-825": {
        "average clique similarity": 0.26493746174149974,
        "clique": [
            "1- We re right by the ",
            "4- If you re reluctant",
            "0- We re just going to"
        ],
        "median tf-idf score": 0.2906493567202501,
        "publications": [
            "Washington Post",
            "NPR",
            "New York Times"
        ],
        "sentences": [
            "\u201cWe\u2019re right by the ocean,\u201d Jordan Guadalupe, an      said Wednesday.",
            "\u201dIf you\u2019re reluctant to evacuate just think of all the people this storm has already killed,\u201d he said.",
            "\u201cWe\u2019re just going to chill,\u201d he said."
        ],
        "tf-idf score": [
            0.2906493567202501,
            0.642775297520929,
            0.234311574991753
        ]
    },
    "0.2653533575732327-3-825": {
        "average clique similarity": 0.2653533575732327,
        "clique": [
            "3-Rick Scott said Tues",
            "4-Rick Scott has just ",
            "2-Rick Scott  who spen"
        ],
        "median tf-idf score": 0.2910460452252902,
        "publications": [
            "Buzzfeed News",
            "NPR",
            "CNN"
        ],
        "sentences": [
            "Rick Scott said Tuesday.",
            "Rick Scott has just three words: \u201dEvacuate, evacuate, evacuate\u201d.",
            "Rick Scott, who spent the better part of the past three days warning residents to evacuate ahead of the Category 4 hurricane, told them Thursday night that the storm is a \u201dmonster\u201d."
        ],
        "tf-idf score": [
            0.2910460452252902,
            0.15695455890432508,
            0.9190521395650785
        ]
    },
    "0.2669100840655282-3-825": {
        "average clique similarity": 0.2669100840655282,
        "clique": [
            "3-If you make a decisi",
            "2- If you decide to ri",
            "4- This storm will kil"
        ],
        "median tf-idf score": 0.2213774694706211,
        "publications": [
            "Buzzfeed News",
            "CNN",
            "NPR"
        ],
        "sentences": [
            "If you make a decision not to leave before the storm, we cannot send someone to save you because you made a bad decision.",
            "\u201dIf you decide to ride it out, do not expect us to be there to help you.",
            "\u201dThis storm will kill you."
        ],
        "tf-idf score": [
            0.34229519979771916,
            0.04050870601486865,
            0.2213774694706211
        ]
    },
    "0.28568508292477274-3-592": {
        "average clique similarity": 0.28568508292477274,
        "clique": [
            "1-Scott declared a sta",
            "2-Pat McCrory declared",
            "4-Updated 1 23 a  m  E"
        ],
        "median tf-idf score": 0.5133024899205182,
        "publications": [
            "Washington Post",
            "NPR",
            "CNN"
        ],
        "sentences": [
            "Scott declared a state of emergency in Florida, as did his counterparts in Georgia, South Carolina and North Carolina.",
            "Pat McCrory declared a state of emergency for the state\u2019s 100 counties.",
            "Updated 1:23 a. m. ET with emergency declaration in Georgia, Late Thursday night President Obama declared a state of emergency in 30 Georgia counties."
        ],
        "tf-idf score": [
            0.6067263245713077,
            0.2592359180035553,
            0.5133024899205182
        ]
    },
    "0.2866793697642816-4-481": {
        "average clique similarity": 0.2866793697642816,
        "clique": [
            "4-The National Hurrica",
            "0-As of Wednesday morn",
            "2-Reports from the sto",
            "1- Reuters    The Nati"
        ],
        "median tf-idf score": 0.9683606525345819,
        "publications": [
            "NPR",
            "CNN",
            "Washington Post",
            "New York Times"
        ],
        "sentences": [
            "The National Hurricane Center explains that the storm is \u201dforecast to take a track roughly parallel to the coastline\u201d.",
            "As of Wednesday morning, the storm, which was downgraded to Category 3, from Category 4, had passed through Cuba, and the National Hurricane Center in Miami warned that a dangerous surge was beginning to spread over the Bahamas, to the north.",
            "Reports from the storm\u2019s path, Here\u2019s what you need to know: \u2022 Matthew remains a Category 4 storm with winds of 130 mph, according to the latest National Hurricane Center advisory.",
            "(Reuters)   The National Hurricane Center reported that the storm had maximum sustained winds near 120 mph on Wednesday with higher gusts, and \u201csome strengthening\u201d was expected in the coming days."
        ],
        "tf-idf score": [
            0.6645404437951425,
            1.0152249364178512,
            0.9578435425498999,
            0.978877762519264
        ]
    },
    "0.28998267358454893-3-585": {
        "average clique similarity": 0.28998267358454893,
        "clique": [
            "4-In Georgia  where th",
            "1- Mic     Georgia Gov",
            "2-Georgia governor   R"
        ],
        "median tf-idf score": 0.10893778640092647,
        "publications": [
            "NPR",
            "Washington Post",
            "CNN"
        ],
        "sentences": [
            "In Georgia, where the coastline is relatively short, Gov.",
            "(Mic  )  Georgia Gov.",
            "Georgia governor: \u2019Remain calm, be prepared\u2019 Gov."
        ],
        "tf-idf score": [
            0.10893778640092647,
            0.08185410583360331,
            0.15038458809157884
        ]
    },
    "0.29184416446256534-3-149": {
        "average clique similarity": 0.29184416446256534,
        "clique": [
            "2- Extremely dangerous",
            "3-That means hurricane",
            "4-The center says hurr"
        ],
        "median tf-idf score": 0.5132560873352434,
        "publications": [
            "CNN",
            "Buzzfeed News",
            "NPR"
        ],
        "sentences": [
            "\u201dExtremely dangerous,   weather conditions are forecast in the next 12 to 24 hours,\u201d the weather service warned.",
            "That means hurricane conditions are expected in 150 miles of Florida beaches in the next 48 hours, rather than just being possible.",
            "The center says hurricane conditions will reach Florida in the next several hours."
        ],
        "tf-idf score": [
            0.18363537748437297,
            0.5582345163887467,
            0.5132560873352434
        ]
    },
    "0.29433166061210336-3-98": {
        "average clique similarity": 0.29433166061210336,
        "clique": [
            "0-Other areas of the S",
            "1-Haley evacuated Char",
            "2-Close to half a mill"
        ],
        "median tf-idf score": 0.6389045039372518,
        "publications": [
            "New York Times",
            "Washington Post",
            "CNN"
        ],
        "sentences": [
            "Other areas of the South Carolina coast will be evacuated on Thursday morning, the governor said.",
            "Haley evacuated Charleston and Beaufort counties on Wednesday afternoon, and she said other areas were expected to evacuate Thursday morning.",
            "Close to half a million people were expected to have evacuated by Thursday, said Kim Stenson, director of South Carolina Emergency Management."
        ],
        "tf-idf score": [
            0.6216529019716729,
            0.6389045039372518,
            0.7083357282566708
        ]
    },
    "0.3021097294108967-3-825": {
        "average clique similarity": 0.3021097294108967,
        "clique": [
            "2-Mandatory evacuation",
            "4-In South Carolina  s",
            "3-  Across Florida  Ge"
        ],
        "median tf-idf score": 0.40676301721652874,
        "publications": [
            "CNN",
            "NPR",
            "Buzzfeed News"
        ],
        "sentences": [
            "Mandatory evacuations in South Carolina, Cars packed highways in South Carolina, where officials gave mandatory evacuation orders for several counties.",
            "In South Carolina, some 1.",
            "\u201d Across Florida, Georgia, North Carolina, and South Carolina, the American Red Cross stood ready with more than 500 disaster workers."
        ],
        "tf-idf score": [
            0.40676301721652874,
            0.14309320468317283,
            0.4272912197615649
        ]
    },
    "0.30662668212634075-3-494": {
        "average clique similarity": 0.30662668212634075,
        "clique": [
            "3- Matthew is forecast",
            "0-Coverage continues h",
            "4-As of late Thursday "
        ],
        "median tf-idf score": 0.7522855923267091,
        "publications": [
            "Buzzfeed News",
            "NPR",
            "New York Times"
        ],
        "sentences": [
            "\u201cMatthew is forecast to move   throughout the central Bahamas during the day today, and then move very near or along the east coast of Florida Thursday and Friday.",
            "Coverage continues here &gt&gt \u2022 \u201cHurricane conditions\u201d are expected in much of the Bahamas Lake Okeechobee, Fla. and a long coastal stretch of the United States that includes Fort Lauderdale, Boca Raton, West Palm Beach and St. Augustine in Florida, and Jekyll Island off Georgia, the National Hurricane Center announced at 5 a. m. The eye of the storm was expected to pass near Grand Bahama Island late Thursday and move \u201cvery close to the east coast of the Florida peninsula\u201d Thursday evening through Friday night.",
            "As of late Thursday morning, the storm is a Category 4 that\u2019s expected to near the Florida coast late Thursday and early Friday, the agency forecasts."
        ],
        "tf-idf score": [
            0.6188181001184154,
            1.709056151083145,
            0.7522855923267091
        ]
    },
    "0.31244694429293846-3-372": {
        "average clique similarity": 0.31244694429293846,
        "clique": [
            "0-Hurricane Matthew  h",
            "2-A direct hit by Matt",
            "1- If Matthew directly"
        ],
        "median tf-idf score": 0.7166059677013401,
        "publications": [
            "CNN",
            "Washington Post",
            "New York Times"
        ],
        "sentences": [
            "Hurricane Matthew, he said, was packing enough strength to cause the kind of \u201cmassive destruction we haven\u2019t seen in years.",
            "A direct hit by Matthew, he said, could lead to \u201dmassive destruction\u201d on a level unseen since Hurricane Andrew in 1992.",
            "\u201cIf Matthew directly impacts Florida, there will be massive destruction that we haven\u2019t seen in years,\u201d Gov."
        ],
        "tf-idf score": [
            0.7790895660179709,
            0.7166059677013401,
            0.410291018881348
        ]
    },
    "0.3197332815217123-3-825": {
        "average clique similarity": 0.3197332815217123,
        "clique": [
            "4- If you don t get ou",
            "2- You still have time",
            "0- Now is the time for"
        ],
        "median tf-idf score": 0.32344548322790423,
        "publications": [
            "NPR",
            "CNN",
            "New York Times"
        ],
        "sentences": [
            "\u201dIf you don\u2019t get out in time, then you might get stuck,\u201d Haley said, according to the Post and Courier.",
            "\u201dYou still have time to leave.",
            "\u201cNow is the time for you to prepare in the event that you have to evacuate,\u201d Mr Obama said."
        ],
        "tf-idf score": [
            0.32344548322790423,
            0.07738817596265118,
            0.3639606029472263
        ]
    },
    "0.328723701355574-3-390": {
        "average clique similarity": 0.328723701355574,
        "clique": [
            "4-The last Category 3 ",
            "0-If Matthew hits Flor",
            "1-If Matthew is a Cate"
        ],
        "median tf-idf score": 0.7230013161421254,
        "publications": [
            "NPR",
            "Washington Post",
            "New York Times"
        ],
        "sentences": [
            "The last Category 3 or higher to hit the U S at all was Wilma in 2005, the AP notes  \u2014   the storm struck in southwest Florida and killed five people.",
            "If Matthew hits Florida directly, it will be the first major hurricane to do so since Wilma in 2005, which caused damage estimated at $21 billion.",
            "If Matthew is a Category 3 or stronger hurricane when it hits Florida, it would be the first major hurricane to make landfall in the country since Hurricane Wilma in 2005."
        ],
        "tf-idf score": [
            0.7230013161421254,
            0.659950457279116,
            0.7543674354022475
        ]
    },
    "0.407066652176265-3-546": {
        "average clique similarity": 0.407066652176265,
        "clique": [
            "3-Don t wait until you",
            "1- For those of you th",
            "0- For those of you th"
        ],
        "median tf-idf score": 0.4143126875201006,
        "publications": [
            "Washington Post",
            "Buzzfeed News",
            "New York Times"
        ],
        "sentences": [
            "Don\u2019t wait until you lose power.",
            "\u201cFor those of you that are wondering whether you should leave or not, I again will tell you that if you do not leave, you are putting a law enforcement officer or a National Guardsman\u2019s life on the line when they have to go back and get you,\u201d she said.",
            "\u201cFor those of you that are wondering whether you should leave or not, I again will tell you that if you do not leave, you are putting a law enforcement officer or a National Guardsman\u2019s life on the line when they have to go back and get you,\u201d Ms Haley said, She estimated that the evacuation would affect about 250, 000 residents and countless tourists."
        ],
        "tf-idf score": [
            0.030003075294804633,
            0.4143126875201006,
            0.6769761457452403
        ]
    },
    "0.41451962317863517-3-825": {
        "average clique similarity": 0.41451962317863517,
        "clique": [
            "2-North Carolina playi",
            "1-  In South Carolina ",
            "4-In South Carolina  G"
        ],
        "median tf-idf score": 0.17998276513852643,
        "publications": [
            "CNN",
            "Washington Post",
            "NPR"
        ],
        "sentences": [
            "North Carolina playing it by ear, Gov.",
            "\u201d In South Carolina, Gov.",
            "In South Carolina, Gov."
        ],
        "tf-idf score": [
            0.15616361986143387,
            0.17998276513852643,
            0.17998276513852643
        ]
    }
}